{
    "items": [
        {
            "id": 0,
            "name": "踏云亭",
            "position": {
                "x": 0.9030000567436218,
                "y": 6.3832292556762699,
                "z": 0.0
            },
            "neighborIDs": [1,2,3,4,5,6]
        },
        {
            "id": 1,
            "name": "重阳阁",
            "position": {
                "x": 0.4220999479293823,
                "y": 5.972733020782471,
                "z": 0.0
            },
            "neighborIDs": [2,3,4]
        },
        {
            "id": 2,
            "name": "观景台",
            "position": {
                "x": -0.4976999759674072,
                "y": 6.2721266746521,
                "z": 0.0
            },
            "neighborIDs": [3,4]
        },
        {
            "id": 3,
            "name": "香炉峰",
            "position": {
                "x": -0.10080000758171082,
                "y": 5.7259674072265629,
                "z": 0.0
            },
            "neighborIDs": [4]
        },
        {
            "id": 4,
            "name": "豫泰门",
            "position": {
                "x": -1.2442500591278077,
                "y": 6.012496471405029,
                "z": 0.0
            },
            "neighborIDs": [6,7,9,10]
        },
        {
            "id": 5,
            "name": "索道上站",
            "position": {
                "x": 0.5166000127792358,
                "y": 5.54937219619751,
                "z": 0.0
            },
            "neighborIDs": [10]
        },
        {
            "id": 6,
            "name": "梅石",
            "position": {
                "x": -0.9397499561309815,
                "y": 5.253487586975098,
                "z": 0.0
            },
            "neighborIDs": [7]
        },
        {
            "id": 7,
            "name": "延月亭",
            "position": {
                "x": -1.4804998636245728,
                "y": 3.8255231380462648,
                "z": 0.0
            },
            "neighborIDs": [8,9,16]
        },
        {
            "id": 8,
            "name": "晞阳阿",
            "position": {
                "x": -1.4206500053405762,
                "y": 3.410348653793335,
                "z": 0.0
            },
            "neighborIDs": [9,11,12]
        },
        {
            "id": 9,
            "name": "香雾窟",
            "position": {
                "x": -0.48719996213912966,
                "y": 3.072362184524536,
                "z": 0.0
            },
            "neighborIDs": [8,10,12,13,14,15]
        },
        {
            "id": 10,
            "name": "西山晴雪",
            "position": {
                "x": 0.21104997396469117,
                "y": 3.0992605686187746,
                "z": 0.0
            },
            "neighborIDs": [9,13,18,27]
        },
        {
            "id": 11,
            "name": "森玉笏",
            "position": {
                "x": -1.5875999927520753,
                "y": 2.6875948905944826,
                "z": 0.0
            },
            "neighborIDs": [12,14,20,21]
        },
        {
            "id": 12,
            "name": "云巢亭",
            "position": {
                "x": -1.238999843597412,
                "y": 2.415100574493408,
                "z": 0.0
            },
            "neighborIDs": [14,21]
        },
        {
            "id": 13,
            "name": "梯云山馆",
            "position": {
                "x": 0.3821999728679657,
                "y": 1.9016880989074708,
                "z": 0.0
            },
            "neighborIDs": [17]
        },
        {
            "id": 14,
            "name": "栖月山庄",
            "position": {
                "x": -1.089900016784668,
                "y": 1.70170259475708,
                "z": 0.0
            },
            "neighborIDs": [15]
        },
        {
            "id": 15,
            "name": "多景亭",
            "position": {
                "x": -0.8379000425338745,
                "y": 1.1847816705703736,
                "z": 0.0
            },
            "neighborIDs": [20]
        },
        {
            "id": 16,
            "name": "山神庙",
            "position": {
                "x": -2.2973999977111818,
                "y": 1.1847816705703736,
                "z": 0.0
            },
            "neighborIDs": [21,24,31]
        },
        {
            "id": 17,
            "name": "重翠庵",
            "position": {
                "x": 0.5438999533653259,
                "y": 1.0690007209777833,
                "z": 0.0
            },
            "neighborIDs": [19]
        },
        {
            "id": 18,
            "name": "芙蓉坪",
            "position": {
                "x": 0.4273499548435211,
                "y": 0.21643191576004029,
                "z": 0.0
            },
            "neighborIDs": [19,20,27]
        },
        {
            "id": 19,
            "name": "烟霏蔚秀",
            "position": {
                "x": -0.2509499788284302,
                "y": 0.41641730070114138,
                "z": 0.0
            },
            "neighborIDs": [20,27,36,37,38,41,47,48]
        },
        {
            "id": 20,
            "name": "玉华岫",
            "position": {
                "x": -0.7864500284194946,
                "y": 0.17082124948501588,
                "z": 0.0
            },
            "neighborIDs": [27,36,37,38,41,47,48]
        },
        {
            "id": 21,
            "name": "阆风亭",
            "position": {
                "x": -1.852199912071228,
                "y": 0.45501095056533816,
                "z": 0.0
            },
            "neighborIDs": [16,22,25]
        },
        {
            "id": 22,
            "name": "雨香馆",
            "position": {
                "x": -2.6081998348236086,
                "y": 0.07375246286392212,
                "z": 0.0
            },
            "neighborIDs": [23,25]
        },
        {
            "id": 23,
            "name": "绚秋林",
            "position": {
                "x": -2.3110499382019045,
                "y": -0.33323514461517336,
                "z": 0.0
            },
            "neighborIDs": [24,26,28,29,36,37,38]
        },
        {
            "id": 24,
            "name": "白松亭",
            "position": {
                "x": -2.569349765777588,
                "y": -0.8945974111557007,
                "z": 0.0
            },
            "neighborIDs": [28,31]
        },
        {
            "id": 25,
            "name": "玉乳泉",
            "position": {
                "x": -1.4710499048233033,
                "y": -0.2876244783401489,
                "z": 0.0
            },
            "neighborIDs": [26]
        },
        {
            "id": 26,
            "name": "致佳亭",
            "position": {
                "x": -1.1801998615264893,
                "y": -0.5390681028366089,
                "z": 0.0
            },
            "neighborIDs": [29,36,37,38]
        },
        {
            "id": 27,
            "name": "隔云钟",
            "position": {
                "x": 0.6404999494552612,
                "y": -0.5846786499023438,
                "z": 0.0
            },
            "neighborIDs": [47,48]
        },
        {
            "id": 28,
            "name": "香山寺",
            "position": {
                "x": -3.2024998664855959,
                "y": -1.650097131729126,
                "z": 0.0
            },
            "neighborIDs": [29,30]
        },
        {
            "id": 29,
            "name": "来青轩",
            "position": {
                "x": -2.4149999618530275,
                "y": -1.8828284740447999,
                "z": 0.0
            },
            "neighborIDs": [36,37,38]
        },
        {
            "id": 30,
            "name": "璎珞岩",
            "position": {
                "x": -2.2596001625061037,
                "y": -2.676921844482422,
                "z": 0.0
            },
            "neighborIDs": [32,33,34,35,39,42,44,45]
        },
        {
            "id": 31,
            "name": "流憩亭",
            "position": {
                "x": -3.8870997428894045,
                "y": -1.9986095428466797,
                "z": 0.0
            },
            "neighborIDs": [32]
        },
        {
            "id": 32,
            "name": "双清别墅",
            "position": {
                "x": -3.467099666595459,
                "y": -2.669905424118042,
                "z": 0.0
            },
            "neighborIDs": [30,33]
        },
        {
            "id": 33,
            "name": "双清别墅东侧平房",
            "position": {
                "x": -3.3190500736236574,
                "y": -3.2768783569335939,
                "z": 0.0
            },
            "neighborIDs": [30,34,35]
        },
        {
            "id": 34,
            "name": "看云起",
            "position": {
                "x": -2.853900194168091,
                "y": -3.606678009033203,
                "z": 0.0
            },
            "neighborIDs": [46]
        },
        {
            "id": 35,
            "name": "翠微亭",
            "position": {
                "x": -2.343600034713745,
                "y": -3.419557571411133,
                "z": 0.0
            },
            "neighborIDs": [30,44,46]
        },
        {
            "id": 36,
            "name": "思亲舍",
            "position": {
                "x": -0.7035000324249268,
                "y": -1.8886759281158448,
                "z": 0.0
            },
            "neighborIDs": [37,38]
        },
        {
            "id": 37,
            "name": "小白楼",
            "position": {
                "x": -0.9880499243736267,
                "y": -1.9214222431182862,
                "z": 0.0
            },
            "neighborIDs": [38,39]
        },
        {
            "id": 38,
            "name": "多云亭",
            "position": {
                "x": -0.5428500175476074,
                "y": -1.9214222431182862,
                "z": 0.0
            },
            "neighborIDs": [40]
        },
        {
            "id": 39,
            "name": "丽瞩楼",
            "position": {
                "x": -0.5102999806404114,
                "y": -2.4640722274780275,
                "z": 0.0
            },
            "neighborIDs": [42,44,45]
        },
        {
            "id": 40,
            "name": "知松园",
            "position": {
                "x": 0.4326000213623047,
                "y": -2.4640722274780275,
                "z": 0.0
            },
            "neighborIDs": [41,43,49]
        },
        {
            "id": 41,
            "name": "问松轩",
            "position": {
                "x": 0.23834998905658723,
                "y": -1.8570992946624756,
                "z": 0.0
            },
            "neighborIDs": [47]
        },
        {
            "id": 42,
            "name": "致远斋",
            "position": {
                "x": -0.1942499876022339,
                "y": -2.909653902053833,
                "z": 0.0
            },
            "neighborIDs": [44,45]
        },
        {
            "id": 43,
            "name": "镇芳楼 镇南房",
            "position": {
                "x": 0.438899964094162,
                "y": -2.909653902053833,
                "z": 0.0
            },
            "neighborIDs": [47,50]
        },
        {
            "id": 44,
            "name": "静翠湖",
            "position": {
                "x": -1.3051499128341675,
                "y": -3.678018093109131,
                "z": 0.0
            },
            "neighborIDs": [42,45,46]
        },
        {
            "id": 45,
            "name": "东宫门",
            "position": {
                "x": -0.34334999322891238,
                "y": -3.678018093109131,
                "z": 0.0
            },
            "neighborIDs": [50]
        },
        {
            "id": 46,
            "name": "青未了",
            "position": {
                "x": -1.3576500415802003,
                "y": -4.304872035980225,
                "z": 0.0
            },
            "neighborIDs": [35,44]
        },
        {
            "id": 47,
            "name": "昭庙",
            "position": {
                "x": 1.1287498474121094,
                "y": -1.4243829250335694,
                "z": 0.0
            },
            "neighborIDs": [48]
        },
        {
            "id": 48,
            "name": "见心斋",
            "position": {
                "x": 1.909949779510498,
                "y": -1.1203114986419678,
                "z": 0.0
            },
            "neighborIDs": [49]
        },
        {
            "id": 49,
            "name": "索道下站",
            "position": {
                "x": 3.0082497596740724,
                "y": -2.0956785678863527,
                "z": 0.0
            },
            "neighborIDs": [50]
        },
        {
            "id": 50,
            "name": "北门",
            "position": {
                "x": 2.6785502433776857,
                "y": -2.702651023864746,
                "z": 0.0
            },
            "neighborIDs": [40,48,49,51]
        },
        {
            "id": 51,
            "name": "碧云寺",
            "position": {
                "x": 4.312349796295166,
                "y": 0.13807517290115357,
                "z": 0.0
            },
            "neighborIDs": [50]
        }
    ]
}